<annotation>
	<folder>images</folder>
	<filename>N98.jpeg</filename>
	<path>C:\Users\Marouane\Desktop\Master_DSBD\S3\PREDICTIVE ANALYSIS\courses\Automatic Number Plate Recognition\practise\1-data_labeling\images\N98.jpeg</path>
	<source>
		<database>Unknown</database>
	</source>
	<size>
		<width>704</width>
		<height>330</height>
		<depth>3</depth>
	</size>
	<segmented>0</segmented>
	<object>
		<name>number_plate</name>
		<pose>Unspecified</pose>
		<truncated>0</truncated>
		<difficult>0</difficult>
		<bndbox>
			<xmin>565</xmin>
			<ymin>209</ymin>
			<xmax>673</xmax>
			<ymax>236</ymax>
		</bndbox>
	</object>
</annotation>
